{
  "type": "mbti",
  "date": "2026-07-25",
  "periods": {
    "daily": {
      "INTJ": {
        "score": 4,
        "keyword": "유연 전략",
        "text": "완벽한 청사진을 세워도 오늘은 변수가 끼어드는 날이에요. 계획을 살짝 내려놓고 흐름에 맞춰 수정하는 쪽이 오히려 결과를 더 좋게 만들어요.",
        "advice": "오늘 하나는 즉흥적으로 결정해보세요.",
        "lucky": { "color": "남색", "number": 3 }
      },
      "INTP": {
        "score": 5,
        "keyword": "직행 실험",
        "text": "머릿속에서 이론을 완성하려다 하루가 다 갈 뻔했는데, 오늘은 손이 먼저 움직이는 게 답이에요. 어설프게라도 시작한 결과물이 생각보다 빨리 답을 보여줘요.",
        "advice": "완벽한 계획 대신 초안부터 써보세요.",
        "lucky": { "color": "회색", "number": 7 }
      },
      "ENTJ": {
        "score": 2,
        "keyword": "위임 감각",
        "text": "모든 지출을 직접 관리하고 싶어도 오늘은 예상 밖 변수로 계산이 살짝 틀어질 수 있어요. 작은 손해는 인정하고 다음 기회를 노리는 리더십을 발휘해보세요.",
        "advice": "큰 결제는 하루만 미뤄보세요.",
        "lucky": { "color": "검정", "number": 1 }
      },
      "ENTP": {
        "score": 4,
        "keyword": "경청 매력",
        "text": "재치 있는 반박이 입안에 맴돌아도 오늘은 참는 게 관계에 득이 돼요. 끝까지 들어주는 모습에 친구가 평소보다 더 마음을 열어줘요.",
        "advice": "대화 중 한 번은 그냥 고개만 끄덕여보세요.",
        "lucky": { "color": "주황", "number": 9 }
      },
      "INFJ": {
        "score": 3,
        "keyword": "자기 돌봄",
        "text": "주변 사람 마음까지 살피느라 정작 본인 컨디션은 뒷전이었던 하루들이 쌓였을 거예요. 오늘은 연락에 신경 쓰지 않고 온전히 혼자만의 시간을 챙겨보세요.",
        "advice": "저녁엔 알림을 잠시 꺼두세요.",
        "lucky": { "color": "보라", "number": 6 }
      },
      "INFP": {
        "score": 5,
        "keyword": "직진 고백",
        "text": "머릿속 시나리오만 백 번 돌리던 마음을 오늘은 직접 꺼내보세요. 솔직한 한마디가 생각보다 훨씬 좋은 반응으로 돌아와요.",
        "advice": "마음을 문자 대신 목소리로 전해보세요.",
        "lucky": { "color": "분홍", "number": 2 }
      },
      "ENFJ": {
        "score": 3,
        "keyword": "선택과 집중",
        "text": "이 사람 저 사람 다 챙기다 보면 정작 진짜 필요한 친구를 놓치기 쉬운 날이에요. 오늘은 딱 한 사람에게만 마음을 쏟아보세요.",
        "advice": "연락 목록에서 한 명만 골라 집중하세요.",
        "lucky": { "color": "노랑", "number": 8 }
      },
      "ENFP": {
        "score": 2,
        "keyword": "미니 투두",
        "text": "새로운 아이디어가 계속 떠올라 정신없이 손댔다 놨다 반복할 수 있는 날이에요. 오늘만큼은 딱 하나만 정해서 끝까지 마무리해보세요.",
        "advice": "할 일 목록에 딱 한 줄만 적어보세요.",
        "lucky": { "color": "초록", "number": 5 }
      },
      "ISTJ": {
        "score": 4,
        "keyword": "원칙 플러스",
        "text": "가계부를 꼬박꼬박 챙기는 습관이 오늘 예상치 못한 지출을 막아줘요. 다만 작은 즐거움 하나엔 원칙을 살짝 풀어줘도 괜찮아요.",
        "advice": "예산 안에서 소소한 사치 하나는 허락하세요.",
        "lucky": { "color": "남색", "number": 4 }
      },
      "ISFJ": {
        "score": 3,
        "keyword": "먼저 표현",
        "text": "상대 기분부터 살피느라 정작 내 마음은 늘 뒤로 미뤄뒀을 거예요. 오늘은 서운했던 것 하나를 먼저 꺼내도 관계가 흔들리지 않아요.",
        "advice": "작은 서운함 하나를 솔직히 말해보세요.",
        "lucky": { "color": "하늘", "number": 6 }
      },
      "ESTJ": {
        "score": 1,
        "keyword": "재미 우선",
        "text": "계획표대로 진도를 빼려다 오늘은 집중력이 자꾸 흐트러질 수 있어요. 효율을 잠깐 내려놓고 흥미로운 부분부터 골라보면 오히려 더 오래 붙잡고 있게 돼요.",
        "advice": "진도표보다 재밌는 챕터부터 펼쳐보세요.",
        "lucky": { "color": "갈색", "number": 1 }
      },
      "ESFJ": {
        "score": 4,
        "keyword": "받는 하루",
        "text": "늘 먼저 챙기던 쪽이었다면 오늘은 반대로 누군가의 배려를 그냥 받아들여보세요. 사양하지 않고 받는 것도 관계를 편안하게 만드는 방법이에요.",
        "advice": "누가 도와준다고 하면 사양 말고 받으세요.",
        "lucky": { "color": "베이지", "number": 7 }
      },
      "ISTP": {
        "score": 5,
        "keyword": "무심한 배려",
        "text": "말없이 툭 던진 도움 한 번이 친구에게 오래 남는 하루예요. 티 내지 않아도 다 알아채는 사람들이 있으니 평소처럼만 행동해도 충분해요.",
        "advice": "말 대신 행동으로 도움을 건네보세요.",
        "lucky": { "color": "은색", "number": 9 }
      },
      "ISFP": {
        "score": 3,
        "keyword": "실용 감각",
        "text": "느낌 가는 대로 움직이고 싶은 마음을 잠시 접고, 오늘은 실용적인 선택 하나가 일을 훨씬 매끄럽게 풀어줘요. 감각은 잠깐 아껴뒀다 나중에 써도 늦지 않아요.",
        "advice": "감보다 체크리스트를 먼저 따라가 보세요.",
        "lucky": { "color": "카키", "number": 3 }
      },
      "ESTP": {
        "score": 2,
        "keyword": "승부수 보류",
        "text": "오늘 당장 질러버리고 싶은 충동이 스멀스멀 올라와도, 경자일의 신중한 기운이 브레이크를 살짝 걸어줘요. 큰 승부수는 하루 미뤄두는 게 훨씬 이득이에요.",
        "advice": "지르고 싶은 소비는 내일로 미뤄보세요.",
        "lucky": { "color": "빨강", "number": 8 }
      },
      "ESFP": {
        "score": 4,
        "keyword": "진심 한마디",
        "text": "분위기를 띄우는 재주는 여전히 빛나지만, 오늘은 화려한 말보다 담백한 진심 한마디가 상대 마음을 더 크게 움직여요. 텐션을 살짝 낮춰도 매력은 그대로예요.",
        "advice": "농담 대신 진심 한마디를 건네보세요.",
        "lucky": { "color": "코랄", "number": 5 }
      }
    }
  }
}
